quark_tagged_text.py
Quark_Xpress_Tags_to_xml-1.1.dist-info/DESCRIPTION.rst
Quark_Xpress_Tags_to_xml-1.1.dist-info/METADATA
Quark_Xpress_Tags_to_xml-1.1.dist-info/RECORD
Quark_Xpress_Tags_to_xml-1.1.dist-info/WHEEL
Quark_Xpress_Tags_to_xml-1.1.dist-info/metadata.json
Quark_Xpress_Tags_to_xml-1.1.dist-info/top_level.txt
