Metadata-Version: 2.0
Name: Quark-Xpress-Tags-to-xml
Version: 1.1
Summary: Convert Quark Xpress Tags to XML
Home-page: UNKNOWN
Author: Guillaume Lepert
Author-email: guillaume.d.lepert@free.fr
License: MIT
Platform: UNKNOWN
Requires-Python: >=3
Requires-Dist: lxml
Requires-Dist: pypeg2
